music_bassline_generator/__init__.py
music_bassline_generator/music_bassline_generator.py
music_bassline_generator-0.2.8.dist-info/licenses/LICENSE
music_bassline_generator-0.2.8.dist-info/METADATA
music_bassline_generator-0.2.8.dist-info/WHEEL
music_bassline_generator-0.2.8.dist-info/top_level.txt
music_bassline_generator-0.2.8.dist-info/RECORD
