Metadata-Version: 2.4
Name: music_bassline_generator
Version: 0.2.8
Summary: Generate musical basslines
Author-email: Gene Boggs <gene.boggs@gmail.com>
License:                     GNU GENERAL PUBLIC LICENSE
Project-URL: Homepage, https://github.com/ology/Python-Music-Bassline-Generator
Project-URL: Repository, https://github.com/ology/Python-Music-Bassline-Generator.git
Project-URL: Issues, https://github.com/ology/Python-Music-Bassline-Generator/issues
Classifier: Development Status :: 2 - Pre-Alpha
Classifier: Programming Language :: Python
Classifier: Programming Language :: Python :: 3
Classifier: Programming Language :: Python :: 3.9
Classifier: Programming Language :: Python :: 3.10
Classifier: Programming Language :: Python :: 3.11
Classifier: Programming Language :: Python :: 3.12
Requires-Python: >=3.9
License-File: LICENSE
Requires-Dist: music21
Requires-Dist: music_voicegen
Requires-Dist: pychord
Dynamic: license-file
